linked_sqlserver_dialect/__init__.py
linked_sqlserver_dialect/base.py
linked_sqlserver_dialect/pyodbc.py
linked_sqlserver_dialect-0.2.1.dist-info/licenses/LICENSE
linked_sqlserver_dialect-0.2.1.dist-info/METADATA
linked_sqlserver_dialect-0.2.1.dist-info/WHEEL
linked_sqlserver_dialect-0.2.1.dist-info/entry_points.txt
linked_sqlserver_dialect-0.2.1.dist-info/top_level.txt
linked_sqlserver_dialect-0.2.1.dist-info/RECORD
