Metadata-Version: 2.4
Name: linked-sqlserver-dialect
Version: 0.2.1
Summary: SQLAlchemy dialect for SQL Server linked servers (reflection via INFORMATION_SCHEMA)
Author: Thomas
License-Expression: MIT
Project-URL: Homepage, https://github.com/tomanizer/linked-sqlserver-dialect
Project-URL: Repository, https://github.com/tomanizer/linked-sqlserver-dialect
Project-URL: Issues, https://github.com/tomanizer/linked-sqlserver-dialect/issues
Keywords: sqlalchemy,sqlserver,mssql,linked-server,pyodbc,dialect
Classifier: Development Status :: 3 - Alpha
Classifier: Intended Audience :: Developers
Classifier: Programming Language :: Python :: 3
Classifier: Programming Language :: Python :: 3.11
Classifier: Programming Language :: Python :: 3.12
Classifier: Topic :: Database
Requires-Python: >=3.11
License-File: LICENSE
Requires-Dist: sqlalchemy>=2.0
Requires-Dist: pyodbc
Provides-Extra: dev
Requires-Dist: pytest>=8.0; extra == "dev"
Requires-Dist: build>=1.2.0; extra == "dev"
Requires-Dist: twine>=5.0.0; extra == "dev"
Dynamic: license-file
